imdm/data_models/generic_models.py
imdm-0.1.1.dist-info/LICENSE
imdm-0.1.1.dist-info/METADATA
imdm-0.1.1.dist-info/WHEEL
imdm-0.1.1.dist-info/RECORD
