Metadata-Version: 2.1
Name: imdm
Version: 0.1.1
Summary: Data models for MRI and image applications
License: MIT
Author: josegcpa
Author-email: jose.almeida@research.fchampalimaud.org
Requires-Python: >=3.10,<4.0
Classifier: License :: OSI Approved :: MIT License
Classifier: Programming Language :: Python :: 3
Classifier: Programming Language :: Python :: 3.10
Classifier: Programming Language :: Python :: 3.11
Requires-Dist: numpy (>=1.24.2,<2.0.0)
Requires-Dist: pillow (>=9.4.0,<10.0.0)
Requires-Dist: pydicom (>=2.3.1,<3.0.0)
Requires-Dist: pytest (>=7.2.2,<8.0.0)
Requires-Dist: ruff (>=0.0.254,<0.0.255)
Requires-Dist: simpleitk (>=2.2.1,<3.0.0)
Requires-Dist: termcolor (>=2.2.0,<3.0.0)
